README.md
setup.py
dynamodb_create_cloudwatch_alarms/__init__.py
dynamodb_create_cloudwatch_alarms/constants.py
dynamodb_create_cloudwatch_alarms/main.py
dynamodb_create_cloudwatch_alarms.egg-info/PKG-INFO
dynamodb_create_cloudwatch_alarms.egg-info/SOURCES.txt
dynamodb_create_cloudwatch_alarms.egg-info/dependency_links.txt
dynamodb_create_cloudwatch_alarms.egg-info/entry_points.txt
dynamodb_create_cloudwatch_alarms.egg-info/requires.txt
dynamodb_create_cloudwatch_alarms.egg-info/top_level.txt