Metadata-Version: 1.1
Name: dynamodb-create-cloudwatch-alarms
Version: 2.4
Summary: AWS DynamoDB Tool for creating Metric Alarms
Home-page: https://github.com/percolate/dynamodb-create-cloudwatch-alarms
Author: Mihailo Pavlisin
Author-email: mihailo@percolate.com
License: GPLv3
Keywords: aws dynamodb alarms cloudwatch boto
Platform: UNKNOWN
Classifier: Development Status :: 4 - Beta
Classifier: Environment :: Console
Classifier: Intended Audience :: System Administrators
Classifier: License :: OSI Approved :: GNU General Public License v3 (GPLv3)
Classifier: Natural Language :: English
Classifier: Operating System :: POSIX
Classifier: Programming Language :: Python
Classifier: Topic :: System :: Systems Administration
